lab08.v
// programa 1
module Counter(input wire clk, reset, enable, load,  output reg[11:0] count);
//contador de 12 bits con entradas de clock, reset, enable y load

  //conteo en cada flanco de reloj
  always @ (posedge clk or posedge reset or posedge enable or posedge load) begin
    if(reset) begin
     count <= 12'd0; // si se resetea empieza en cero
    end
    else if(clk & enable & ~load) begin
        #2 count <= count + 12'd1; // si esta en enable cuenta el contador sino no cuenta
    end
    else if(clk & load & enable) begin
        #2 count <= 12'd34; //precargando que empiece en 34 base 10
    end
  end

endmodule

//programa 2
module Memory (input wire [11:0] address, output wire [7:0] word);//memoria rom
  reg [7:0] mem [0:4095];// creacion de arreglo de memoria
  initial begin
      $readmemb("memory.list", mem);//lectura del archivo de datos
  end
  assign word = mem[address];// resultado leido de la memoria
endmodule

// programa 3
module ALU(input wire [3:0] A, B, input wire [2:0] F, output reg [3:0] Resultado);//implementacion de la ALU

// parametros tabla 5.1 libro
  parameter AND1 = 3'd0;
  parameter OR1 = 3'd1;
  parameter ADD = 3'd2;
  parameter AND2 = 3'd4;
  parameter OR2 = 3'd5;
  parameter SUBTRACT = 3'd6;
  parameter SLT = 3'd7;

  always @(*) begin// operaciones a realizar con la ALU con un switch case
    case(F)
    AND1:  assign Resultado = (A & B);
    OR1:   assign Resultado = (A | B);
    ADD:  assign Resultado = A + B;
    AND2: assign Resultado = (A & ~B);
    OR2:  assign Resultado = (A | ~B);
    SUBTRACT: assign Resultado = A - B;
    SLT: assign Resultado = (A > B) ? 4'd0 : 4'd1;
    default: Resultado = 4'd0;
    endcase
  end

endmodule

lab08_tb.v
module testbench();
reg clock, reset, enable, load;//variables para el contador
wire [11:0] salida;

wire [7:0]word;
reg  [11:0]address;//variables para la memoria
integer i;

reg [2:0] F;
reg [3:0] A, B;
wire [3:0] salida_2;//variables para el ALU

always//instanciacion del clock
  begin
    clock <= 1;
    #1 clock <= ~clock;// se realiza el cambio del reloj
    #1;
end

Counter Contador(clock, reset, enable, load, salida);
Memory  Memoria(address, word);
ALU     ALU1(A, B, F, salida_2);// instanciacion de los modulos de cada ejercicio

initial begin// test de contador
  $display("Contador\n");
  $display("CLK Reset | Enable Load | Contador");
  $display("----------|-------------|--------------");
  $monitor("%b     %b   |    %b     %b  | %b", clock,reset,enable,load,salida);
  #2 reset = 1;
  #2 enable = 0; load = 0; reset = 0;
  #2; #2;
  #2 enable = 1; load = 0;
  #2; #2; #2; #2;
  #2 load = 1;
  #2 load = 0 ;
  #2; #2; #2;
  #2 enable = 0;
  #2; #2; #2;

end

initial begin//test de memoria
  #38
  $display(" Memoria ROM ");
  $display("Address       |    Word   ");
  $display("--------------|-------------");
  $monitor("%b  |   %b", address, word);

  for (i = 0; i < 10; i++) begin// lectura de los 10 primeros datos de la memoria ROM
    #2 address =  i;
  end
end

initial begin//test del ALU
    #60
    $display("\n");
    $display(" ALU ");
    $display("\n");
    $display(" A        B    | F   |  Y ");
    $display(" ----------------------------");
    $monitor(" %b    %b  | %b |  %b ", A, B, F, salida_2);

    A[3] = 0; A[2] = 0; A[1] = 1; A[0] = 0; B[3] = 0; B[2] = 1; B[1] = 0; B[0] = 1;
    #2  F[2] = 0; F[1] = 0; F[0] = 0;
    #2  F[2] = 0; F[1] = 0; F[0] = 1;
    #2  F[2] = 0; F[1] = 1; F[0] = 0;
    #2  F[2] = 1; F[1] = 0; F[0] = 0;
    #2  F[2] = 1; F[1] = 0; F[0] = 1;
    #2  F[2] = 1; F[1] = 1; F[0] = 0;
    #2  F[2] = 1; F[1] = 1; F[0] = 1;
    #1  F[2] = 0; F[1] = 0; F[0] = 0;
    #2  A[3] = 1; A[2] = 0; A[1] = 1; A[0] = 0;
    #2  F[2] = 1; F[1] = 1; F[0] = 1;
    #2 $finish;
  end

  initial begin//ejecutar GTKWave para diagramas de timing.
    $dumpfile("lab08_tb.vcd");
    $dumpvars(0, testbench);
  end

endmodule

lab08.vcd
$date
	Sat Oct 24 19:55:48 2020
$end
$version
	Icarus Verilog
$end
$timescale
	1ps
$end
$scope module testbench $end
$var wire 8 ! word [7:0] $end
$var wire 4 " salida_2 [3:0] $end
$var wire 12 # salida [11:0] $end
$var reg 4 $ A [3:0] $end
$var reg 4 % B [3:0] $end
$var reg 3 & F [2:0] $end
$var reg 12 ' address [11:0] $end
$var reg 1 ( clock $end
$var reg 1 ) enable $end
$var reg 1 * load $end
$var reg 1 + reset $end
$var integer 32 , i [31:0] $end
$scope module ALU1 $end
$var wire 4 - A [3:0] $end
$var wire 4 . B [3:0] $end
$var wire 3 / F [2:0] $end
$var reg 4 0 Resultado [3:0] $end
$upscope $end
$scope module Contador $end
$var wire 1 ( clk $end
$var wire 1 ) enable $end
$var wire 1 * load $end
$var wire 1 + reset $end
$var reg 12 1 count [11:0] $end
$upscope $end
$scope module Memoria $end
$var wire 12 2 address [11:0] $end
$var wire 8 3 word [7:0] $end
$upscope $end
$upscope $end
$enddefinitions $end
#0
$dumpvars
bx 3
bx 2
bx 1
bx 0
bx /
bx .
bx -
bx ,
x+
x*
x)
1(
bx '
bx &
bx %
bx $
bx #
bx "
bx !
$end
#1
0(
#2
b0 #
b0 1
1(
1+
#3
0(
#4
1(
0+
0*
0)
#5
0(
#6
1(
#7
0(
#8
1(
#9
0(
#10
1(
1)
#11
0(
#12
1(
b1 #
b1 1
#13
0(
#14
1(
b10 #
b10 1
#15
0(
#16
1(
b11 #
b11 1
#17
0(
#18
1(
b100 #
b100 1
#19
0(
#20
1(
b101 #
b101 1
1*
#21
0(
#22
1(
b100010 #
b100010 1
0*
#23
0(
#24
1(
b100011 #
b100011 1
#25
0(
#26
1(
b100100 #
b100100 1
#27
0(
#28
1(
b100101 #
b100101 1
#29
0(
#30
1(
b100110 #
b100110 1
0)
#31
0(
#32
1(
#33
0(
#34
1(
#35
0(
#36
1(
#37
0(
#38
1(
b0 ,
#39
0(
#40
1(
b1 ,
b10100010 !
b10100010 3
b0 '
b0 2
#41
0(
#42
1(
b10 ,
b10010010 !
b10010010 3
b1 '
b1 2
#43
0(
#44
1(
b11 ,
b100111 !
b100111 3
b10 '
b10 2
#45
0(
#46
1(
b100 ,
b1001011 !
b1001011 3
b11 '
b11 2
#47
0(
#48
1(
b101 ,
b101000 !
b101000 3
b100 '
b100 2
#49
0(
#50
1(
b110 ,
b10111 !
b10111 3
b101 '
b101 2
#51
0(
#52
1(
b111 ,
b10000100 !
b10000100 3
b110 '
b110 2
#53
0(
#54
1(
b1000 ,
b1010011 !
b1010011 3
b111 '
b111 2
#55
0(
#56
1(
b1001 ,
b1011110 !
b1011110 3
b1000 '
b1000 2
#57
0(
#58
1(
b1010 ,
b10110101 !
b10110101 3
b1001 '
b1001 2
#59
0(
#60
1(
b101 %
b101 .
b10 $
b10 -
#61
0(
#62
1(
b0 "
b0 0
b0 &
b0 /
#63
0(
#64
1(
b111 "
b111 0
b1 &
b1 /
#65
0(
#66
1(
b10 &
b10 /
#67
0(
#68
1(
b10 "
b10 0
b100 &
b100 /
#69
0(
#70
1(
b1010 "
b1010 0
b101 &
b101 /
#71
0(
#72
1(
b1101 "
b1101 0
b110 &
b110 /
#73
0(
#74
1(
b1 "
b1 0
b111 &
b111 /
#75
0(
#76
1(
b0 "
b0 0
b0 &
b0 /
#77
0(
#78
1(
b1010 $
b1010 -
#79
0(
#80
1(
b111 &
b111 /
